ags/__init__.py
ags/client.py
ags/feature_flag.py
ags/logger.py
ags/oidc_client.py
ags/route.py
ags_client-0.1.11.dist-info/DESCRIPTION.rst
ags_client-0.1.11.dist-info/LICENSE.txt
ags_client-0.1.11.dist-info/METADATA
ags_client-0.1.11.dist-info/RECORD
ags_client-0.1.11.dist-info/WHEEL
ags_client-0.1.11.dist-info/metadata.json
ags_client-0.1.11.dist-info/top_level.txt
tests/__init__.py
tests/conftest.py
tests/test_authz_flow.py
tests/test_feature_switch.py
tests/test_oidc_client.py
tests/test_router.py
