Metadata-Version: 2.0
Name: ags-client
Version: 0.1.11
Summary: Client library for accessing GaaP services
Home-page: https://github.com/crossgovernmentservices/ags_client_python
Author: Andy Driver
Author-email: andy.driver@digital.cabinet-office.gov.uk
License: LICENSE
Keywords: python,gds,govuk
Platform: any
Classifier: Programming Language :: Python
Classifier: Programming Language :: Python :: 3.5
Classifier: License :: OSI Approved :: MIT License
Classifier: Operating System :: OS Independent
Classifier: Development Status :: 3 - Alpha
Classifier: Environment :: Web Environment
Classifier: Intended Audience :: Developers
Classifier: Natural Language :: English
Classifier: Topic :: Internet :: WWW/HTTP
Classifier: Topic :: Software Development :: Libraries :: Python Modules
Requires-Dist: Werkzeug (>=0.11.11)
Requires-Dist: beaker (>=1.8.1)
Requires-Dist: oic (>=0.9.1.0)
Requires-Dist: requests (>=2.7,<3)
